<?xml version="1.0"?>
<VOTABLE version="1.1" xsi:schemaLocation="http://www.ivoa.net/xml/VOTable/v1.1" xmlns:xsi="http://www.w3.org/2001/XMLSchema-instance">
  <INFO name="QUERY_STATUS" value="OK"/>
  <RESOURCE type="results">
    <TABLE utype="photdm:PhotometryFilter.transmissionCurve.spectrum">
    <PARAM name="FilterProfileService" value="ivo://svo/fps" ucd="meta.ref.ivorn" utype="PhotometryFilter.fpsIdentifier" datatype="char" arraysize="*"/>
    <PARAM name="filterID" value="GTC/OSIRIS.sdss_g_filter" ucd="meta.id" utype="photdm:PhotometryFilter.identifier" datatype="char" arraysize="*"/>
    <PARAM name="WavelengthUnit" value="Angstrom" ucd="meta.unit" utype="PhotometryFilter.SpectralAxis.unit" datatype="char" arraysize="*"/>
    <PARAM name="WavelengthUCD" value="em.wl" ucd="meta.ucd" utype="PhotometryFilter.SpectralAxis.UCD" datatype="char" arraysize="*"/>
    <PARAM name="Description" value="GTC, Osiris,  SDSS g (filter only)" ucd="meta.note" utype="photdm:PhotometryFilter.description" datatype="char" arraysize="*"/>
    <PARAM name="PhotSystem" value="OSIRIS" utype="photdm:PhotometricSystem.description" datatype="char" arraysize="*">
       <DESCRIPTION>Photometric system</DESCRIPTION>
    </PARAM>
    <PARAM name="DetectorType" value="1" utype="photdm:PhotometricSystem.detectorType" datatype="char" arraysize="*">
       <DESCRIPTION>Detector type. 0:Energy counter, 1:Photon counter.</DESCRIPTION>
    </PARAM>
    <PARAM name="Band" value="g" utype="photdm:PhotometryFilter.bandName" datatype="char" arraysize="*"/>
    <PARAM name="Instrument" value="Osiris" ucd="instr" datatype="char" arraysize="*">
       <DESCRIPTION>Instrument</DESCRIPTION>
    </PARAM>
    <PARAM name="Facility" value="GTC" ucd="instr.obsty" datatype="char" arraysize="*">
       <DESCRIPTION>Observational facility</DESCRIPTION>
    </PARAM>
    <PARAM name="ProfileReference" value="http://www.gtc.iac.es/en/pages/instrumentation/osiris.php" datatype="char" arraysize="*"/>
    <PARAM name="Description" value="GTC, Osiris,  SDSS g (filter only)" ucd="meta.note" utype="photdm:PhotometryFilter.description" datatype="char" arraysize="*"/>
    <PARAM name="components" value="Filter" datatype="char" arraysize="*">
       <DESCRIPTION>Transmission components</DESCRIPTION>
    </PARAM>
    <PARAM name="WavelengthRef" value="4787.5780860188" unit="Angstrom" ucd="em.wl" datatype="double" >
       <DESCRIPTION>Reference wavelength. Defined as the same than the pivot wavelength.</DESCRIPTION>
    </PARAM>
    <PARAM name="WavelengthMean" value="4847.5493981624" unit="Angstrom" ucd="em.wl" utype="photdm:PhotometryFilter.SpectralAxis.Coverage.Location.Value" datatype="double" >
       <DESCRIPTION>Mean wavelength. Defined as integ[x*filter(x) dx]/integ[filter(x) dx]</DESCRIPTION>
    </PARAM>
    <PARAM name="WavelengthEff" value="4745.422243561" unit="Angstrom" ucd="em.wl.effective" datatype="double" >
       <DESCRIPTION>Effective wavelength. Defined as integ[x*filter(x)*vega(x) dx]/integ[filter(x)*vega(x) dx]</DESCRIPTION>
    </PARAM>
    <PARAM name="WavelengthMin" value="3800" unit="Angstrom" ucd="em.wl;stat.min" utype="photdm:PhotometryFilter.SpectralAxis.Coverage.Bounds.Start" datatype="double" >
       <DESCRIPTION>Minimum filter wavelength. Defined as the first lambda value with a transmission at least 1% of maximum transmission</DESCRIPTION>
    </PARAM>
    <PARAM name="WavelengthMax" value="5805.8431714024" unit="Angstrom" ucd="em.wl;stat.max" utype="photdm:PhotometryFilter.SpectralAxis.Coverage.Bounds.Stop" datatype="double" >
       <DESCRIPTION>Maximum filter wavelength. Defined as the last lambda value with a transmission at least 1% of maximum transmission</DESCRIPTION>
    </PARAM>
    <PARAM name="WidthEff" value="1321.1908854829" unit="Angstrom" ucd="instr.bandwidth" utype="photdm:PhotometryFilter.SpectralAxis.Coverage.Bounds.Extent" datatype="double" >
       <DESCRIPTION>Effective width. Defined as integ[x*filter(x) dx].\nEquivalent to the horizontal size of a rectangle with height equal to maximum transmission and with the same area that the one covered by the filter transmission curve.</DESCRIPTION>
    </PARAM>
    <PARAM name="WavelengthCen" value="4814.9490942537" unit="Angstrom" ucd="em.wl" datatype="double" >
       <DESCRIPTION>Central wavelength. Defined as the central wavelength between the two points defining FWMH</DESCRIPTION>
    </PARAM>
    <PARAM name="WavelengthPivot" value="4787.5780860188" unit="Angstrom" ucd="em.wl" datatype="double" >
       <DESCRIPTION>Peak wavelength. Defined as sqrt{integ[x*filter(x) dx]/integ[filter(x) dx/x]}</DESCRIPTION>
    </PARAM>
    <PARAM name="WavelengthPeak" value="4880" unit="Angstrom" ucd="em.wl" datatype="double" >
       <DESCRIPTION>Peak wavelength. Defined as the lambda value with larger transmission</DESCRIPTION>
    </PARAM>
    <PARAM name="WavelengthPhot" value="4784.8722281782" unit="Angstrom" ucd="em.wl" datatype="double" >
       <DESCRIPTION>Photon distribution based effective wavelength. Defined as integ[x^2*filter(x)*vega(x) dx]/integ[x*filter(x)*vega(x) dx]</DESCRIPTION>
    </PARAM>
    <PARAM name="FWHM" value="1531.6920433578" unit="Angstrom" ucd="instr.bandwidth" datatype="double" >
       <DESCRIPTION>Full width at half maximum. Defined as the difference between the two wavelengths for which filter transmission is half maximum</DESCRIPTION>
    </PARAM>
    <PARAM name="Fsun" value="188.30057461807" unit="erg/cm2/s/A" ucd="phot.flux.density" datatype="double" >
       <DESCRIPTION>Sun flux</DESCRIPTION>
    </PARAM>
    <PARAM name="PhotCalID" value="GTC/OSIRIS.sdss_g_filter/Vega" ucd="meta.id" utype="photdm:PhotCal.identifier" datatype="char" arraysize="*"/>
    <PARAM name="MagSys" value="Vega" ucd="meta.code" utype="photdm:PhotCal.MagnitudeSystem.type" datatype="char" arraysize="*"/>
    <PARAM name="ZeroPoint" value="3906.8517754763" unit="Jy" ucd="phot.flux.density" utype="photdm:PhotCal.ZeroPoint.Flux.value" datatype="double" />
    <PARAM name="ZeroPointUnit" value="Jy" ucd="meta.unit" utype="photdm:PhotCal.ZeroPoint.Flux.unit" datatype="char" arraysize="*"/>
    <PARAM name="ZeroPointType" value="Pogson" ucd="meta.code" utype="photdm:PhotCal.ZeroPoint.type" datatype="char" arraysize="*"/>
      <FIELD name="Wavelength" utype="spec:Data.SpectralAxis.Value" ucd="em.wl" unit="Angstrom" datatype="double"/>
      <FIELD name="Transmission" utype="spec:Data.FluxAxis.Value" ucd="phys.transmission" unit="" datatype="double"/>
      <DATA>
        <TABLEDATA>
          <TR>
            <TD>3800.000000</TD>
            <TD>0.012039</TD>
          </TR>
          <TR>
            <TD>3810.000000</TD>
            <TD>0.024791</TD>
          </TR>
          <TR>
            <TD>3820.000000</TD>
            <TD>0.007698</TD>
          </TR>
          <TR>
            <TD>3830.000000</TD>
            <TD>0.015600</TD>
          </TR>
          <TR>
            <TD>3840.000000</TD>
            <TD>0.012872</TD>
          </TR>
          <TR>
            <TD>3850.000000</TD>
            <TD>0.004510</TD>
          </TR>
          <TR>
            <TD>3860.000000</TD>
            <TD>0.000535</TD>
          </TR>
          <TR>
            <TD>3870.000000</TD>
            <TD>0.009773</TD>
          </TR>
          <TR>
            <TD>3880.000000</TD>
            <TD>0.020824</TD>
          </TR>
          <TR>
            <TD>3890.000000</TD>
            <TD>0.013686</TD>
          </TR>
          <TR>
            <TD>3900.000000</TD>
            <TD>0.015594</TD>
          </TR>
          <TR>
            <TD>3910.000000</TD>
            <TD>0.006300</TD>
          </TR>
          <TR>
            <TD>3920.000000</TD>
            <TD>0.013754</TD>
          </TR>
          <TR>
            <TD>3930.000000</TD>
            <TD>0.015697</TD>
          </TR>
          <TR>
            <TD>3940.000000</TD>
            <TD>0.014343</TD>
          </TR>
          <TR>
            <TD>3950.000000</TD>
            <TD>0.026067</TD>
          </TR>
          <TR>
            <TD>3960.000000</TD>
            <TD>0.052115</TD>
          </TR>
          <TR>
            <TD>3970.000000</TD>
            <TD>0.069951</TD>
          </TR>
          <TR>
            <TD>3980.000000</TD>
            <TD>0.101252</TD>
          </TR>
          <TR>
            <TD>3990.000000</TD>
            <TD>0.145162</TD>
          </TR>
          <TR>
            <TD>4000.000000</TD>
            <TD>0.202681</TD>
          </TR>
          <TR>
            <TD>4010.000000</TD>
            <TD>0.221653</TD>
          </TR>
          <TR>
            <TD>4020.000000</TD>
            <TD>0.272173</TD>
          </TR>
          <TR>
            <TD>4030.000000</TD>
            <TD>0.353016</TD>
          </TR>
          <TR>
            <TD>4040.000000</TD>
            <TD>0.392407</TD>
          </TR>
          <TR>
            <TD>4050.000000</TD>
            <TD>0.414343</TD>
          </TR>
          <TR>
            <TD>4060.000000</TD>
            <TD>0.462659</TD>
          </TR>
          <TR>
            <TD>4070.000000</TD>
            <TD>0.491652</TD>
          </TR>
          <TR>
            <TD>4080.000000</TD>
            <TD>0.491716</TD>
          </TR>
          <TR>
            <TD>4090.000000</TD>
            <TD>0.512632</TD>
          </TR>
          <TR>
            <TD>4100.000000</TD>
            <TD>0.555010</TD>
          </TR>
          <TR>
            <TD>4110.000000</TD>
            <TD>0.563400</TD>
          </TR>
          <TR>
            <TD>4120.000000</TD>
            <TD>0.580785</TD>
          </TR>
          <TR>
            <TD>4130.000000</TD>
            <TD>0.596213</TD>
          </TR>
          <TR>
            <TD>4140.000000</TD>
            <TD>0.588191</TD>
          </TR>
          <TR>
            <TD>4150.000000</TD>
            <TD>0.599982</TD>
          </TR>
          <TR>
            <TD>4160.000000</TD>
            <TD>0.584525</TD>
          </TR>
          <TR>
            <TD>4170.000000</TD>
            <TD>0.590250</TD>
          </TR>
          <TR>
            <TD>4180.000000</TD>
            <TD>0.605915</TD>
          </TR>
          <TR>
            <TD>4190.000000</TD>
            <TD>0.615849</TD>
          </TR>
          <TR>
            <TD>4200.000000</TD>
            <TD>0.613269</TD>
          </TR>
          <TR>
            <TD>4210.000000</TD>
            <TD>0.619788</TD>
          </TR>
          <TR>
            <TD>4220.000000</TD>
            <TD>0.621447</TD>
          </TR>
          <TR>
            <TD>4230.000000</TD>
            <TD>0.620793</TD>
          </TR>
          <TR>
            <TD>4240.000000</TD>
            <TD>0.628173</TD>
          </TR>
          <TR>
            <TD>4250.000000</TD>
            <TD>0.636808</TD>
          </TR>
          <TR>
            <TD>4260.000000</TD>
            <TD>0.640998</TD>
          </TR>
          <TR>
            <TD>4270.000000</TD>
            <TD>0.668690</TD>
          </TR>
          <TR>
            <TD>4280.000000</TD>
            <TD>0.674482</TD>
          </TR>
          <TR>
            <TD>4290.000000</TD>
            <TD>0.672146</TD>
          </TR>
          <TR>
            <TD>4300.000000</TD>
            <TD>0.677930</TD>
          </TR>
          <TR>
            <TD>4310.000000</TD>
            <TD>0.698716</TD>
          </TR>
          <TR>
            <TD>4320.000000</TD>
            <TD>0.696273</TD>
          </TR>
          <TR>
            <TD>4330.000000</TD>
            <TD>0.704173</TD>
          </TR>
          <TR>
            <TD>4340.000000</TD>
            <TD>0.720777</TD>
          </TR>
          <TR>
            <TD>4350.000000</TD>
            <TD>0.721244</TD>
          </TR>
          <TR>
            <TD>4360.000000</TD>
            <TD>0.727967</TD>
          </TR>
          <TR>
            <TD>4370.000000</TD>
            <TD>0.728738</TD>
          </TR>
          <TR>
            <TD>4380.000000</TD>
            <TD>0.722613</TD>
          </TR>
          <TR>
            <TD>4390.000000</TD>
            <TD>0.727853</TD>
          </TR>
          <TR>
            <TD>4400.000000</TD>
            <TD>0.729063</TD>
          </TR>
          <TR>
            <TD>4410.000000</TD>
            <TD>0.726632</TD>
          </TR>
          <TR>
            <TD>4420.000000</TD>
            <TD>0.734694</TD>
          </TR>
          <TR>
            <TD>4430.000000</TD>
            <TD>0.735773</TD>
          </TR>
          <TR>
            <TD>4440.000000</TD>
            <TD>0.727891</TD>
          </TR>
          <TR>
            <TD>4450.000000</TD>
            <TD>0.728149</TD>
          </TR>
          <TR>
            <TD>4460.000000</TD>
            <TD>0.732634</TD>
          </TR>
          <TR>
            <TD>4470.000000</TD>
            <TD>0.734866</TD>
          </TR>
          <TR>
            <TD>4480.000000</TD>
            <TD>0.732886</TD>
          </TR>
          <TR>
            <TD>4490.000000</TD>
            <TD>0.738801</TD>
          </TR>
          <TR>
            <TD>4500.000000</TD>
            <TD>0.740924</TD>
          </TR>
          <TR>
            <TD>4510.000000</TD>
            <TD>0.748921</TD>
          </TR>
          <TR>
            <TD>4520.000000</TD>
            <TD>0.751818</TD>
          </TR>
          <TR>
            <TD>4530.000000</TD>
            <TD>0.757066</TD>
          </TR>
          <TR>
            <TD>4540.000000</TD>
            <TD>0.757239</TD>
          </TR>
          <TR>
            <TD>4550.000000</TD>
            <TD>0.768797</TD>
          </TR>
          <TR>
            <TD>4560.000000</TD>
            <TD>0.767920</TD>
          </TR>
          <TR>
            <TD>4570.000000</TD>
            <TD>0.767396</TD>
          </TR>
          <TR>
            <TD>4580.000000</TD>
            <TD>0.777165</TD>
          </TR>
          <TR>
            <TD>4590.000000</TD>
            <TD>0.770064</TD>
          </TR>
          <TR>
            <TD>4600.000000</TD>
            <TD>0.784969</TD>
          </TR>
          <TR>
            <TD>4610.000000</TD>
            <TD>0.785727</TD>
          </TR>
          <TR>
            <TD>4620.000000</TD>
            <TD>0.782980</TD>
          </TR>
          <TR>
            <TD>4630.000000</TD>
            <TD>0.786271</TD>
          </TR>
          <TR>
            <TD>4640.000000</TD>
            <TD>0.781599</TD>
          </TR>
          <TR>
            <TD>4650.000000</TD>
            <TD>0.784984</TD>
          </TR>
          <TR>
            <TD>4660.000000</TD>
            <TD>0.787260</TD>
          </TR>
          <TR>
            <TD>4670.000000</TD>
            <TD>0.785169</TD>
          </TR>
          <TR>
            <TD>4680.000000</TD>
            <TD>0.786089</TD>
          </TR>
          <TR>
            <TD>4690.000000</TD>
            <TD>0.781988</TD>
          </TR>
          <TR>
            <TD>4700.000000</TD>
            <TD>0.785575</TD>
          </TR>
          <TR>
            <TD>4710.000000</TD>
            <TD>0.782831</TD>
          </TR>
          <TR>
            <TD>4720.000000</TD>
            <TD>0.780782</TD>
          </TR>
          <TR>
            <TD>4730.000000</TD>
            <TD>0.786548</TD>
          </TR>
          <TR>
            <TD>4740.000000</TD>
            <TD>0.786926</TD>
          </TR>
          <TR>
            <TD>4750.000000</TD>
            <TD>0.786426</TD>
          </TR>
          <TR>
            <TD>4760.000000</TD>
            <TD>0.793945</TD>
          </TR>
          <TR>
            <TD>4770.000000</TD>
            <TD>0.793391</TD>
          </TR>
          <TR>
            <TD>4780.000000</TD>
            <TD>0.799275</TD>
          </TR>
          <TR>
            <TD>4790.000000</TD>
            <TD>0.798406</TD>
          </TR>
          <TR>
            <TD>4800.000000</TD>
            <TD>0.805187</TD>
          </TR>
          <TR>
            <TD>4810.000000</TD>
            <TD>0.813000</TD>
          </TR>
          <TR>
            <TD>4820.000000</TD>
            <TD>0.814230</TD>
          </TR>
          <TR>
            <TD>4830.000000</TD>
            <TD>0.816421</TD>
          </TR>
          <TR>
            <TD>4840.000000</TD>
            <TD>0.822159</TD>
          </TR>
          <TR>
            <TD>4850.000000</TD>
            <TD>0.820622</TD>
          </TR>
          <TR>
            <TD>4860.000000</TD>
            <TD>0.823001</TD>
          </TR>
          <TR>
            <TD>4870.000000</TD>
            <TD>0.823794</TD>
          </TR>
          <TR>
            <TD>4880.000000</TD>
            <TD>0.824751</TD>
          </TR>
          <TR>
            <TD>4890.000000</TD>
            <TD>0.821976</TD>
          </TR>
          <TR>
            <TD>4900.000000</TD>
            <TD>0.819207</TD>
          </TR>
          <TR>
            <TD>4910.000000</TD>
            <TD>0.813656</TD>
          </TR>
          <TR>
            <TD>4920.000000</TD>
            <TD>0.812946</TD>
          </TR>
          <TR>
            <TD>4930.000000</TD>
            <TD>0.805059</TD>
          </TR>
          <TR>
            <TD>4940.000000</TD>
            <TD>0.795853</TD>
          </TR>
          <TR>
            <TD>4950.000000</TD>
            <TD>0.791436</TD>
          </TR>
          <TR>
            <TD>4960.000000</TD>
            <TD>0.785326</TD>
          </TR>
          <TR>
            <TD>4970.000000</TD>
            <TD>0.775377</TD>
          </TR>
          <TR>
            <TD>4980.000000</TD>
            <TD>0.766386</TD>
          </TR>
          <TR>
            <TD>4990.000000</TD>
            <TD>0.758971</TD>
          </TR>
          <TR>
            <TD>5000.000000</TD>
            <TD>0.748581</TD>
          </TR>
          <TR>
            <TD>5010.000000</TD>
            <TD>0.740413</TD>
          </TR>
          <TR>
            <TD>5020.000000</TD>
            <TD>0.735307</TD>
          </TR>
          <TR>
            <TD>5030.000000</TD>
            <TD>0.730701</TD>
          </TR>
          <TR>
            <TD>5040.000000</TD>
            <TD>0.721641</TD>
          </TR>
          <TR>
            <TD>5050.000000</TD>
            <TD>0.719218</TD>
          </TR>
          <TR>
            <TD>5060.000000</TD>
            <TD>0.716614</TD>
          </TR>
          <TR>
            <TD>5070.000000</TD>
            <TD>0.712324</TD>
          </TR>
          <TR>
            <TD>5080.000000</TD>
            <TD>0.711186</TD>
          </TR>
          <TR>
            <TD>5090.000000</TD>
            <TD>0.714253</TD>
          </TR>
          <TR>
            <TD>5100.000000</TD>
            <TD>0.716779</TD>
          </TR>
          <TR>
            <TD>5110.000000</TD>
            <TD>0.719454</TD>
          </TR>
          <TR>
            <TD>5120.000000</TD>
            <TD>0.723091</TD>
          </TR>
          <TR>
            <TD>5130.000000</TD>
            <TD>0.726830</TD>
          </TR>
          <TR>
            <TD>5140.000000</TD>
            <TD>0.730847</TD>
          </TR>
          <TR>
            <TD>5150.000000</TD>
            <TD>0.735876</TD>
          </TR>
          <TR>
            <TD>5160.000000</TD>
            <TD>0.741941</TD>
          </TR>
          <TR>
            <TD>5170.000000</TD>
            <TD>0.748418</TD>
          </TR>
          <TR>
            <TD>5180.000000</TD>
            <TD>0.755596</TD>
          </TR>
          <TR>
            <TD>5190.000000</TD>
            <TD>0.760079</TD>
          </TR>
          <TR>
            <TD>5200.000000</TD>
            <TD>0.763319</TD>
          </TR>
          <TR>
            <TD>5210.000000</TD>
            <TD>0.764426</TD>
          </TR>
          <TR>
            <TD>5220.000000</TD>
            <TD>0.765424</TD>
          </TR>
          <TR>
            <TD>5230.000000</TD>
            <TD>0.764112</TD>
          </TR>
          <TR>
            <TD>5240.000000</TD>
            <TD>0.759003</TD>
          </TR>
          <TR>
            <TD>5250.000000</TD>
            <TD>0.754295</TD>
          </TR>
          <TR>
            <TD>5260.000000</TD>
            <TD>0.746084</TD>
          </TR>
          <TR>
            <TD>5270.000000</TD>
            <TD>0.733248</TD>
          </TR>
          <TR>
            <TD>5280.000000</TD>
            <TD>0.718398</TD>
          </TR>
          <TR>
            <TD>5290.000000</TD>
            <TD>0.702597</TD>
          </TR>
          <TR>
            <TD>5300.000000</TD>
            <TD>0.684496</TD>
          </TR>
          <TR>
            <TD>5310.000000</TD>
            <TD>0.663580</TD>
          </TR>
          <TR>
            <TD>5320.000000</TD>
            <TD>0.644739</TD>
          </TR>
          <TR>
            <TD>5330.000000</TD>
            <TD>0.625776</TD>
          </TR>
          <TR>
            <TD>5340.000000</TD>
            <TD>0.605658</TD>
          </TR>
          <TR>
            <TD>5350.000000</TD>
            <TD>0.587884</TD>
          </TR>
          <TR>
            <TD>5360.000000</TD>
            <TD>0.569913</TD>
          </TR>
          <TR>
            <TD>5370.000000</TD>
            <TD>0.553937</TD>
          </TR>
          <TR>
            <TD>5380.000000</TD>
            <TD>0.540847</TD>
          </TR>
          <TR>
            <TD>5390.000000</TD>
            <TD>0.527564</TD>
          </TR>
          <TR>
            <TD>5400.000000</TD>
            <TD>0.518701</TD>
          </TR>
          <TR>
            <TD>5410.000000</TD>
            <TD>0.510619</TD>
          </TR>
          <TR>
            <TD>5420.000000</TD>
            <TD>0.502485</TD>
          </TR>
          <TR>
            <TD>5430.000000</TD>
            <TD>0.498034</TD>
          </TR>
          <TR>
            <TD>5440.000000</TD>
            <TD>0.495215</TD>
          </TR>
          <TR>
            <TD>5450.000000</TD>
            <TD>0.494193</TD>
          </TR>
          <TR>
            <TD>5460.000000</TD>
            <TD>0.495593</TD>
          </TR>
          <TR>
            <TD>5470.000000</TD>
            <TD>0.499327</TD>
          </TR>
          <TR>
            <TD>5480.000000</TD>
            <TD>0.503357</TD>
          </TR>
          <TR>
            <TD>5490.000000</TD>
            <TD>0.508966</TD>
          </TR>
          <TR>
            <TD>5500.000000</TD>
            <TD>0.515535</TD>
          </TR>
          <TR>
            <TD>5510.000000</TD>
            <TD>0.520626</TD>
          </TR>
          <TR>
            <TD>5520.000000</TD>
            <TD>0.525056</TD>
          </TR>
          <TR>
            <TD>5530.000000</TD>
            <TD>0.524444</TD>
          </TR>
          <TR>
            <TD>5540.000000</TD>
            <TD>0.517886</TD>
          </TR>
          <TR>
            <TD>5550.000000</TD>
            <TD>0.506350</TD>
          </TR>
          <TR>
            <TD>5560.000000</TD>
            <TD>0.485154</TD>
          </TR>
          <TR>
            <TD>5570.000000</TD>
            <TD>0.454737</TD>
          </TR>
          <TR>
            <TD>5580.000000</TD>
            <TD>0.415791</TD>
          </TR>
          <TR>
            <TD>5590.000000</TD>
            <TD>0.372835</TD>
          </TR>
          <TR>
            <TD>5600.000000</TD>
            <TD>0.328732</TD>
          </TR>
          <TR>
            <TD>5610.000000</TD>
            <TD>0.285887</TD>
          </TR>
          <TR>
            <TD>5620.000000</TD>
            <TD>0.244303</TD>
          </TR>
          <TR>
            <TD>5630.000000</TD>
            <TD>0.207119</TD>
          </TR>
          <TR>
            <TD>5640.000000</TD>
            <TD>0.173905</TD>
          </TR>
          <TR>
            <TD>5650.000000</TD>
            <TD>0.144683</TD>
          </TR>
          <TR>
            <TD>5660.000000</TD>
            <TD>0.121975</TD>
          </TR>
          <TR>
            <TD>5670.000000</TD>
            <TD>0.100935</TD>
          </TR>
          <TR>
            <TD>5680.000000</TD>
            <TD>0.083442</TD>
          </TR>
          <TR>
            <TD>5690.000000</TD>
            <TD>0.070785</TD>
          </TR>
          <TR>
            <TD>5700.000000</TD>
            <TD>0.059009</TD>
          </TR>
          <TR>
            <TD>5710.000000</TD>
            <TD>0.048738</TD>
          </TR>
          <TR>
            <TD>5720.000000</TD>
            <TD>0.040008</TD>
          </TR>
          <TR>
            <TD>5730.000000</TD>
            <TD>0.033404</TD>
          </TR>
          <TR>
            <TD>5740.000000</TD>
            <TD>0.027675</TD>
          </TR>
          <TR>
            <TD>5750.000000</TD>
            <TD>0.022520</TD>
          </TR>
          <TR>
            <TD>5760.000000</TD>
            <TD>0.018442</TD>
          </TR>
          <TR>
            <TD>5770.000000</TD>
            <TD>0.015817</TD>
          </TR>
          <TR>
            <TD>5780.000000</TD>
            <TD>0.013108</TD>
          </TR>
          <TR>
            <TD>5790.000000</TD>
            <TD>0.010853</TD>
          </TR>
          <TR>
            <TD>5800.000000</TD>
            <TD>0.008885</TD>
          </TR>
          <TR>
            <TD>5810.000000</TD>
            <TD>0.007794</TD>
          </TR>
          <TR>
            <TD>5820.000000</TD>
            <TD>0.006475</TD>
          </TR>
          <TR>
            <TD>5830.000000</TD>
            <TD>0.004964</TD>
          </TR>
          <TR>
            <TD>5840.000000</TD>
            <TD>0.004518</TD>
          </TR>
        </TABLEDATA>
      </DATA>
    </TABLE>
  </RESOURCE>
</VOTABLE>
